{
  "festival": "footprints",
  "name": "Footprints Festival",
  "year": 2026,
  "generated_at": "2025-12-13T16:04:33.731019+00:00",
  "config_properties": {
    "name": "Footprints Festival",
    "year": 2026,
    "base_url": "https://www.tivolivredenburg.nl",
    "lineup_url": "https://www.tivolivredenburg.nl/agenda/50573414/footprints-festival-21-02-2026",
    "artist_path": "",
    "slug": "footprints",
    "bio_language": "Dutch",
    "rating_boost": 1.5,
    "description": "A curated discovery festival at TivoliVredenburg in Utrecht, showcasing emerging international artists across diverse genres.",
    "official_spotify_playlist": "https://open.spotify.com/playlist/2Qt2F5Mwnsd56LFfzagivS",
    "spotify_playlist_id": "https://open.spotify.com/playlist/2lWvCj3mbc0Xn4uN7HeTNX"
  },
  "stats": {
    "total_artists": 11,
    "genre_counts": {
      "Electronic": 3,
      "Psychedelic": 2,
      "Indie Pop": 2,
      "Jazz": 2,
      "Anatolian rock": 1,
      "psychedelic folk": 1,
      "80s-inspired": 1,
      "minimalist electropop": 1,
      "Malian desert blues": 1,
      "Indie": 1,
      "World Music": 1,
      "Traditional Iranian": 1,
      "Armenian Folk": 1,
      "Gospel": 1,
      "Hip-Hop": 1,
      "Grime": 1,
      "Afrobeat": 1,
      "Classical": 1,
      "MPB": 1,
      "Psychedelic Folk": 1,
      "R&B": 1,
      "Experimental": 1
    },
    "dj_count": 0,
    "country_counts": {
      "Germany": 4,
      "Netherlands": 1,
      "Spain": 1,
      "France": 1,
      "Iran": 1,
      "Turkey": 1,
      "UK": 1,
      "Nigeria": 1,
      "Brazil": 1,
      "Belgium": 1
    },
    "gender_counts": {
      "Female": 2,
      "Male": 8,
      "Mixed": 1
    },
    "poc_counts": {
      "Yes": 7,
      "No": 4
    },
    "average_rating": 7.73,
    "rating_counts": {
      "9-10": 1,
      "8-9": 8,
      "6-7": 2
    },
    "has_spotify_links": 0,
    "year": 2026
  },
  "previous_year_comparison": {},
  "ai_profile": "**Footprints Festival 2026: A Celebration of Diversity and Innovation in Music**\n\nThe Footprints Festival 2026 brings together an eclectic lineup of 11 artists from 10 different countries, showcasing a rich tapestry of global sounds. From Germany to Nigeria, Brazil to Iran, the festival's roster reflects a melting pot of cultural influences, with genres spanning from electronic and indie pop to Malian desert blues, Anatolian rock, and traditional Iranian music. This year’s festival emphasizes musical exploration, with a strong presence of electronic (3 artists) and psychedelic sounds (2 artists), complemented by jazz, world music, and experimental styles.\n\nTrue to its name, Footprints Festival continues to leave a mark by championing diversity and inclusion. Seven of the featured artists identify as people of color, and the lineup includes a mix of male, female, and mixed-gender acts, highlighting a commitment to representation. While male artists form the majority, the inclusion of female and mixed-gender acts adds depth to the event’s creative vision, ensuring a dynamic and multifaceted experience for attendees.\n\nWith an impressive average rating of 7.73 and a focus on innovative, genre-blurring performances, Footprints Festival 2026 is set to be a vibrant celebration of music’s ability to unite cultures and push boundaries. Whether it’s the hypnotic rhythms of Afrobeat, the soulful strains of gospel, or the minimalist allure of electropop, this year’s lineup promises a diverse and unforgettable journey for music lovers.",
  "start_date": "2026-02-21",
  "end_date": "2026-02-21"
}